MANIFEST.in
README.md
setup.py
docs/Makefile
docs/conf.py
docs/index.rst
docs/make.bat
docs/troubleshoot.rst
example_project/__init__.py
example_project/pipelines.py
example_project/settings.py
example_project/spiders/__init__.py
example_project/spiders/example.py
scrapy_sentry/__init__.py
scrapy_sentry/extensions.py
scrapy_sentry/middlewares.py
scrapy_sentry/utils.py
scrapy_sentry.egg-info/PKG-INFO
scrapy_sentry.egg-info/SOURCES.txt
scrapy_sentry.egg-info/dependency_links.txt
scrapy_sentry.egg-info/requires.txt
scrapy_sentry.egg-info/top_level.txt